blockdiag_magic/__init__.py
blockdiag_magic/blockdiag.py
blockdiagMagic-0.0.3.dist-info/METADATA
blockdiagMagic-0.0.3.dist-info/WHEEL
blockdiagMagic-0.0.3.dist-info/top_level.txt
blockdiagMagic-0.0.3.dist-info/RECORD
