Metadata-Version: 2.1
Name: blockdiagMagic
Version: 0.0.3
Summary: IPython magics for rendering blockdiag family diagrams.
Home-page: UNKNOWN
Author: Tony Hirst
Author-email: tony.hirst@gmail.com
License: UNKNOWN
Platform: UNKNOWN
Requires-Dist: blockdiag
Requires-Dist: seqdiag
Requires-Dist: nwdiag
Requires-Dist: actdiag
